{"box":[{"id":1,"patent_number":"11009981","name":"Narayan Anand P","description":"Inventor","execution_date":"2004-12-10","recorded":"","recorded_date":"","type":"Inventor","document_file":"","document":"","date_1":"2004-12-10","assignment_no":0,"box_type":1,"shape":"rectangle","dimension":"100x30","segment":0,"border_color":"#363636","border_linepx":"1","background_color":"#222222","subCol":1,"mainCol":1,"entryDateFormatted":"2004-12-10","inTypes":[],"outTypes":["Ownership"],"dottedOnly":1,"securityOnly":0,"step":-1,"x":174,"y":60},{"id":2,"patent_number":"11009981","name":"Olson Eric S","description":"Inventor","execution_date":"2004-12-10","recorded":"","recorded_date":"","type":"Inventor","document_file":"","document":"","date_1":"2004-12-10","assignment_no":0,"box_type":1,"shape":"rectangle","dimension":"100x30","segment":0,"border_color":"#363636","border_linepx":"1","background_color":"#222222","subCol":2,"mainCol":1,"entryDateFormatted":"2004-12-10","inTypes":[],"outTypes":["Ownership"],"dottedOnly":1,"securityOnly":0,"step":-1,"x":434,"y":60,"connectLeft":[[174,180,"2005-04-04","Ownership","Tensorcomm Inc"]],"connectLeft_short":["2005-04-04"]},{"id":3,"patent_number":"11009981","name":"Tensorcomm Inc","description":"Ownership","execution_date":"2005-04-04","recorded":"2005-10-07","recorded_date":"2005-10-07","type":"Ownership","document_file":"https://patentrack.com/resources/shared/data/assignment-pat-17069-370.pdf","document":"https://patentrack.com/resources/shared/data/assignment-pat-17069-370.pdf","date_1":"2005-04-04","assignment_no":1,"box_type":2,"shape":"rectangle","dimension":"100x30","segment":1,"border_color":"#363636","border_linepx":"1","background_color":"#222222","subCol":1,"mainCol":1,"entryDateFormatted":"2005-04-04","inTypes":["Ownership"],"outTypes":["Ownership"],"dottedOnly":1,"securityOnly":0,"step":1,"x":174,"y":180,"connectRight":[[434,60,"2005-04-04","Ownership","Olson Eric S"],[734,240,"2010-04-05","Ownership","Thomas John"]],"connectRight_short":["2005-04-04","2010-04-05"]},{"id":4,"patent_number":"11009981","name":"Thomas John","description":"Ownership","execution_date":"NaN-NaN-NaN","recorded":"0000-00-00","recorded_date":"0000-00-00","type":2,"document_file":"https://patentrack.com/resources/shared/data/assignment-pat-24202-617.pdf","document":"https://patentrack.com/resources/shared/data/assignment-pat-24202-617.pdf","date_1":"0000-00-00","assignment_no":0,"box_type":5,"shape":"rectangle","dimension":"100x30","segment":3,"border_color":"#363636","border_linepx":"1","background_color":"#222222","subCol":1,"mainCol":3,"entryDateFormatted":"NaN-NaN-NaN","inTypes":[],"outTypes":["Ownership"],"dottedOnly":1,"securityOnly":1,"step":2,"x":734,"y":240,"connectLeft":[[174,180,"2010-04-05","Ownership","Tensorcomm Inc"]],"connectLeft_short":["2010-04-05"]},{"id":5,"patent_number":"11009981","name":"Rambus Inc","description":"Ownership","execution_date":"2010-04-05","recorded":"2010-04-09","recorded_date":"2010-04-09","type":"Ownership","document_file":"https://patentrack.com/resources/shared/data/assignment-pat-24202-630.pdf","document":"https://patentrack.com/resources/shared/data/assignment-pat-24202-630.pdf","date_1":"2010-04-05","assignment_no":3,"box_type":2,"shape":"rectangle","dimension":"100x30","segment":1,"border_color":"#363636","border_linepx":"1","background_color":"#222222","subCol":1,"mainCol":1,"entryDateFormatted":"2010-04-05","inTypes":["Ownership"],"outTypes":[],"dottedOnly":1,"securityOnly":0,"step":3,"x":174,"y":420}],"inventor_boxes":[{"id":1,"patent_number":"11009981","name":"Narayan Anand P","description":"Inventor","execution_date":"2004-12-10","recorded":"","recorded_date":"","type":"Inventor","document_file":"","document":"","date_1":"2004-12-10","assignment_no":0,"box_type":1},{"id":2,"patent_number":"11009981","name":"Olson Eric S","description":"Inventor","execution_date":"2004-12-10","recorded":"","recorded_date":"","type":"Inventor","document_file":"","document":"","date_1":"2004-12-10","assignment_no":0,"box_type":1}],"connection":[{"id":1,"assignment_no1":1,"color":"#E60000","type":"Ownership","type_line":"Solid","ref_id":0,"start_id":2,"end_id":3,"box_creator_id":3,"box_creator_id2":0,"popup":["17069-370"],"comment":[{"17069-370":["",""]}],"user_files":[""],"tooltip":"Ownership","date":"2005-04-04","date_1":1112572800,"document1":"https://patentrack.com/resources/shared/data/assignment-pat-17069-370.pdf","document2":"","note1":"","pdf1":"","note2":"","pdf2":"","popuptop":"17069-370","popupbottom":"","step":1,"test2":[[434,96],[434,116],[174,104],[174,144]],"test":[[434,96],[434,116],[319,190],[269,190]]},{"id":2,"assignment_no1":1,"color":"#E60000","type":"Ownership","type_line":"Solid","ref_id":0,"start_id":1,"end_id":3,"box_creator_id":0,"box_creator_id2":0,"popup":["17069-370"],"comment":[{"17069-370":["",""]}],"user_files":[""],"tooltip":"Ownership","date":"2005-04-05","date_1":1112659200,"document1":"https://patentrack.com/resources/shared/data/assignment-pat-17069-370.pdf","document2":"","note1":"","pdf1":"","note2":"","pdf2":"","popuptop":"17069-370","popupbottom":"","step":1,"test2":[[174,96],[174,116],[174,124],[174,144]],"test":[[174,96],[174,116],[174,124],[174,144]]},{"id":3,"assignment_no1":2,"color":"#E60000","type":"Ownership","type_line":"Solid","ref_id":0,"start_id":4,"end_id":3,"box_creator_id":0,"box_creator_id2":4,"popup":["24202-617"],"comment":[{"24202-617":["",""]}],"user_files":[""],"tooltip":"Ownership","date":"2010-04-05","date_1":1270425600,"document1":"https://patentrack.com/resources/shared/data/assignment-pat-24202-617.pdf","document2":"","note1":"","pdf1":"","note2":"","pdf2":"","popuptop":"24202-617","popupbottom":"","step":2,"test2":[[639,220],[579,220],[289,170],[269,170]],"test":[[639,230],[589,230],[319,190],[269,190]]},{"id":4,"assignment_no1":3,"color":"#E60000","type":"Ownership","type_line":"Solid","ref_id":0,"start_id":3,"end_id":5,"box_creator_id":5,"box_creator_id2":0,"popup":["24202-630"],"comment":[{"24202-630":["",""]}],"user_files":[""],"tooltip":"Ownership","date":"2010-04-05","date_1":1270425600,"document1":"https://patentrack.com/resources/shared/data/assignment-pat-24202-630.pdf","document2":"","note1":"","pdf1":"","note2":"","pdf2":"","popuptop":"24202-630","popupbottom":"","step":3,"test2":[[174,216],[174,236],[174,364],[174,384]],"test":[[174,216],[174,236],[174,364],[174,384]]},{"id":5,"assignment_no1":4,"color":"#E60000","type":"Ownership","type_line":"Solid","ref_id":0,"start_id":3,"end_id":5,"box_creator_id":0,"box_creator_id2":0,"popup":["24706-648"],"comment":[{"24706-648":["",""]}],"user_files":[""],"tooltip":"Ownership","date":"2010-04-05","date_1":1270425600,"document1":"https://patentrack.com/resources/shared/data/assignment-pat-24706-648.pdf","document2":"","note1":"","pdf1":"","note2":"","pdf2":"","popuptop":"24706-648","popupbottom":"","step":3,"test2":[[174,216],[174,236],[174,364],[174,384]],"test":[[174,216],[174,236],[174,364],[174,384]]}],"popup":[{"id":"17069-370","displayId":"17069-370","reelNo":"17069","frameNo":"370","recordedDate":"2005-10-07","pageCount":"3","conveyanceText":"ASSIGNMENT OF ASSIGNORS INTEREST (SEE DOCUMENT FOR DETAILS).","corrName":"STEVEN J SHATTIL","corrAddress1":"1490 W. 121ST AVENUE, STE 202","corrAddress2":"WESTMINSTER, CO 80234","patAssignorEarliestExDate":"2005-04-04","patAssignorName":["Olson Eric S","Narayan Anand P"],"patAssigneeName":["Tensorcomm Inc"],"patAssigneeAddress1":["1490 W. 121ST AVENUE, STE 202"],"patAssigneeAddress2":[""],"patAssigneeCity":["WESTMINSTER"],"patAssigneeState":["COLORADO"],"patAssigneeCountryName":["\r"],"patAssigneePostcode":["80234"],"applNum":["11009981"],"filingDate":["2004-12-10"],"intlRegNum":["NULL"],"inventionTitle":["Interference cancellation in a receive diversity system"],"issueDate":["0000-00-00"],"patNum":["NULL"],"pctNum":["NULL"],"publDate":["2006-06-15"],"publNum":["2006012568"],"inventors":["NULL"],"applNumSize":1,"patNumSize":1,"inventionTitleFirst":"Interference cancellation in a receive diversity system","applNumFirst":"11009981","filingDateFirst":"2004-12-10","intlPublDateFirst":"0001-01-01T00:00:00Z","intlRegNumFirst":"NULL","issueDateFirst":"0000-00-00","patNumFirst":"","publDateFirst":"2006-06-15","publNumFirst":"2006012568"},{"id":"24202-617","displayId":"24202-617","reelNo":"24202","frameNo":"617","recordedDate":"2010-04-09","pageCount":"6","conveyanceText":"ASSIGNMENT OF ASSIGNORS INTEREST (SEE DOCUMENT FOR DETAILS).","corrName":"BARCELO & HARRISON, LLP","corrAddress1":"2901 WEST COAST HIGHWAY, SUITE 200","corrAddress2":"NEWPORT BEACH, CA 92663","patAssignorEarliestExDate":"2010-04-05","patAssignorName":["Thomas John"],"patAssigneeName":["Tensorcomm Inc"],"patAssigneeAddress1":["1490 WEST 121ST AVENUE, SUITE 105"],"patAssigneeAddress2":[""],"patAssigneeCity":["WESTMINSTER"],"patAssigneeState":["COLORADO"],"patAssigneeCountryName":["\r"],"patAssigneePostcode":["80234"],"applNum":["10838924","10935015","10935669","10959618","11003881","11005679","11009981","11012817","11035141","11049112","11103138","11192763","11204606","11223713","11233636","11253045","11266928","11272411","11287175","11301771","11398229","11432580","11451685","11451688","11451932","11452027","11475458","11479401","11491674","11509920","11522074","11858074","11893707","12274551","12707507","12727880","12731779","12731915","12731960"],"filingDate":["2004-05-03","2004-09-07","2004-09-07","2004-10-06","2004-12-03","2004-12-07","2004-12-10","2004-12-14","2005-01-13","2005-04-11","2005-04-11","2005-07-29","2005-08-15","2005-09-09","2005-09-23","2005-10-18","2005-11-04","2005-11-10","2005-11-23","2005-12-13","2006-04-05","2006-05-11","2006-06-13","2006-06-13","2006-06-13","2006-06-13","2006-08-28","2006-06-29","2006-07-24","2006-08-25","2006-09-15","2007-09-19","2007-08-17","2008-11-20","2010-02-17","2010-03-19","2010-03-25","2010-03-25","2010-03-25"],"intlRegNum":["NULL","NULL","NULL","NULL","NULL","NULL","NULL","NULL","NULL","NULL","NULL","NULL","NULL","NULL","NULL","NULL","NULL","NULL","NULL","NULL","NULL","NULL","NULL","NULL","NULL","NULL","NULL","NULL","NULL","NULL","NULL","NULL","NULL","NULL","NULL","NULL","NULL","NULL","NULL"],"inventionTitle":["Systems and methods for location estimation in spread spectrum communication systems","INTERFERENCE MATRIX CONSTRUCTION","SYSTEMS AND METHODS FOR PARALLEL SIGNAL CANCELLATION","ORTHOGONALIZATION AND DIRECTIONAL FILTERING","Systems and methods for serial cancellation","SYSTEMS AND METHODS FOR ANALOG TO DIGITAL CONVERSION WITH A SIGNAL CANCELLATION SYSTEM OF A RECEIVER","Interference cancellation in a receive diversity system","Gain control for interference cancellation","Interference cancellation in adjoint operators for communication receivers","Systems and methods for searching interference canceled data","SERIAL CANCELLATION RECEIVER DESIGN FOR A CODED SIGNAL PROCESSING ENGINE","INTERFERENCE CANCELLATION WITHIN WIRELESS TRANSCEIVERS","ADVANCED SIGNAL PROCESSORS FOR INTERFERENCE CANCELLATION IN BASEBAND RECEIVERS","Interpolator using splines generated from an integrator stack seeded at input sample points","Optimal feedback weighting for soft-decision cancellers","Complementary linear feedback shift registers for generating advance timing masks","SOFT WEIGHTED INTERFERENCE CANCELLATION FOR CDMA SYSTEMS","VARIABLE INTERFERENCE CANCELLATION TECHNOLOGY FOR CDMA SYSTEMS","SYSTEMS AND METHODS FOR IMPLEMENTING CORDIC ROTATIONS FOR PROJECTORS AND RELATED OPERATORS","Conflict-free memory for fast walsh and inverse fast walsh transforms","Multiplication by one from a set of constants using simple circuitry","INTERFERENCE CANCELLATION IN VARIABLE CODELENGTH SYSTEMS FOR MULTI-ACCESS COMMUNICATION","ITERATIVE INTERFERENCE CANCELLATION USING MIXED FEEDBACK WEIGHTS AND STABILIZING STEP SIZES","ITERATIVE INTERFERENCE CANCELLATION USING MIXED FEEDBACK WEIGHTS AND STABILIZING STEP SIZES","ITERATIVE INTERFERENCE CANCELLATION USING MIXED FEEDBACK WEIGHTS AND STABILIZING STEP SIZES","ITERATIVE INTERFERENCE CANCELLATION USING MIXED FEEDBACK WEIGHTS AND STABILIZING STEP SIZES","Iterative interference cancellation for MIMO-OFDM receivers","INTER-SYMBOL INTERFERENCE CANCELLATION FOR WIRELESS MULTIPLE ACCESS","ITERATIVE INTERFERENCE CANCELLER FOR WIRELESS MULTIPLE-ACCESS SYSTEMS WITH MULTIPLE RECEIVE ANTENNAS","ITERATIVE INTERFERENCE CANCELLER FOR WIRELESS MULTIPLE-ACCESS SYSTEMS EMPLOYING CLOSED LOOP TRANSMIT DIVERSITY","Virtual reference timing for multi-time based systems","METHODS FOR MANAGING ALIGNMENT AND LATENCY IN INTERFERENCE CANCELLATION","METHODS FOR ESTIMATION AND INTERFERENCE CANCELLATION FOR SIGNAL PROCESSING","SYSTEMS AND METHODS FOR CONTROL OF ADVANCED RECEIVERS","ITERATIVE INTERFERENCE CANCELLATION FOR MIMO-OFDM RECEIVERS","INTERFERENCE CANCELLATION IN VARIABLE CODELENGTH SYSTEMS FOR MULTI-ACESS COMMUNICATION","ITERATIVE INTERFERENCE CANCELLATION USING MIXED FEEDBACK WEIGHTS AND STABILIZING STEP SIZES","ITERATIVE INTERFERENCE CANCELLATION USING MIXED FEEDBACK WEIGHTS AND STABILIZING STEP SIZES","INTER-SYMBOL INTERFERENCE CANCELLATION FOR WIRELESS MULTIPLE ACCESS"],"issueDate":["0000-00-00","2009-08-18","2009-01-06","2007-08-21","0000-00-00","2009-01-13","0000-00-00","0000-00-00","0000-00-00","0000-00-00","2008-04-15","2008-12-09","2010-08-31","0000-00-00","2014-06-24","0000-00-00","2011-01-25","2010-10-05","2010-10-19","0000-00-00","0000-00-00","2010-04-13","2011-08-02","2010-04-20","2010-05-04","2010-05-11","0000-00-00","2010-06-08","2010-11-02","2009-11-24","0000-00-00","2011-12-27","2011-08-23","2012-05-15","2012-07-10","2011-11-22","0000-00-00","2012-10-30","0000-00-00"],"patNum":["NULL","7577186","7474690","7260506","NULL","7477710","NULL","NULL","NULL","NULL","7359465","7463609","7787572","NULL","8761321","NULL","7876810","7808937","7818357","NULL","NULL","7697595","7991088","7702048","7711075","7715508","NULL","7733941","7826516","7623602","NULL","8085889","8005128","8179946","8218697","8064498","NULL","8300745","NULL"],"pctNum":["NULL","NULL","NULL","NULL","NULL","NULL","NULL","NULL","NULL","NULL","NULL","NULL","NULL","NULL","NULL","NULL","NULL","NULL","NULL","NULL","NULL","NULL","NULL","NULL","NULL","NULL","NULL","NULL","NULL","NULL","NULL","NULL","NULL","NULL","NULL","NULL","NULL","NULL","NULL"],"publDate":["2004-10-21","2005-02-10","2005-02-10","2005-04-07","2005-06-09","2005-07-28","2006-06-15","2005-05-12","2006-07-13","2005-08-04","2005-08-18","2007-02-01","2006-10-12","2007-03-15","2006-10-12","2007-07-19","2006-10-12","2006-10-12","2007-06-07","2007-09-06","2007-10-11","2007-11-15","2007-05-17","2007-05-17","2007-05-17","2007-05-17","2007-05-17","2007-05-17","2007-05-17","2007-05-17","2008-03-20","0000-00-00","0000-00-00","2009-06-04","2010-08-19","2010-09-23","2010-07-15","2010-09-02","2010-09-02"],"publNum":["2004020823","2005003106","2005003102","2005007584","2005012308","2005016303","2006012568","2005010127","2006015328","2005016935","2005018049","2007002529","2006022790","2007006139","2006022790","2007016840","2006022785","2006022773","2007013024","2007020879","2007023981","2007026370","2007011013","2007011013","2007011013","2007011013","2007011013","2007011019","2007011013","2007011013","2008006918","NULL","NULL","2009014177","2010020885","2010023898","2010017785","2010022082","2010022082"],"inventors":["NULL"],"applNumSize":39,"patNumSize":39,"inventionTitleFirst":"Systems and methods for location estimation in spread spectrum communication systems","applNumFirst":"10838924","filingDateFirst":"2004-05-03","intlPublDateFirst":"0001-01-01T00:00:00Z","intlRegNumFirst":"NULL","issueDateFirst":"0000-00-00","patNumFirst":"","publDateFirst":"2004-10-21","publNumFirst":"2004020823"},{"id":"24202-630","displayId":"24202-630","reelNo":"24202","frameNo":"630","recordedDate":"2010-04-09","pageCount":"22","conveyanceText":"ASSIGNMENT OF ASSIGNORS INTEREST (SEE DOCUMENT FOR DETAILS).","corrName":"BARCELO & HARRISON, LLP","corrAddress1":"2901 WEST COAST HIGHWAY, SUITE 200","corrAddress2":"NEWPORT BEACH, CA 92663","patAssignorEarliestExDate":"2010-04-05","patAssignorName":["Tensorcomm Inc"],"patAssigneeName":["Rambus Inc"],"patAssigneeAddress1":["4440 EL CAMINE REAL"],"patAssigneeAddress2":[""],"patAssigneeCity":["LOS ALTOS"],"patAssigneeState":["CALIFORNIA"],"patAssigneeCountryName":["\r"],"patAssigneePostcode":["94022"],"applNum":["09612602","09765553","09988218","09988219","10141999","10178541","10247836","10294834","10669954","10686359","10686828","10686829","10699360","10763346","10838924","10935015","10935669","10959618","11003881","11005679","11009981","11012817","11035141","11049112","11100935","11100940","11103138","11192763","11204606","11223713","11233636","11253045","11266928","11272411","11287175","11301771","11398229","11432580","11451685","11451688","11451932","11452027","11475458","11479401","11491674","11509920","11522074","11858074","11893707","12274551","12707507","12727880","12731779","12731915","12731960"],"filingDate":["2000-07-07","2001-01-18","2001-11-19","2001-11-19","2002-05-08","2002-06-25","2002-09-20","2002-11-15","2003-09-23","2003-10-15","2003-10-15","2003-10-15","2003-10-31","2004-01-23","2004-05-03","2004-09-07","2004-09-07","2004-10-06","2004-12-03","2004-12-07","2004-12-10","2004-12-14","2005-01-13","2005-04-11","2005-04-07","2005-04-07","2005-04-11","2005-07-29","2005-08-15","2005-09-09","2005-09-23","2005-10-18","2005-11-04","2005-11-10","2005-11-23","2005-12-13","2006-04-05","2006-05-11","2006-06-13","2006-06-13","2006-06-13","2006-06-13","2006-08-28","2006-06-29","2006-07-24","2006-08-25","2006-09-15","2007-09-19","2007-08-17","2008-11-20","2010-02-17","2010-03-19","2010-03-25","2010-03-25","2010-03-25"],"intlRegNum":["NULL","NULL","NULL","NULL","NULL","NULL","NULL","NULL","NULL","NULL","NULL","NULL","NULL","NULL","NULL","NULL","NULL","NULL","NULL","NULL","NULL","NULL","NULL","NULL","NULL","NULL","NULL","NULL","NULL","NULL","NULL","NULL","NULL","NULL","NULL","NULL","NULL","NULL","NULL","NULL","NULL","NULL","NULL","NULL","NULL","NULL","NULL","NULL","NULL","NULL","NULL","NULL","NULL","NULL","NULL"],"inventionTitle":["RAKE RECEIVER FOR SPREAD SPECTRUM SIGNAL DEMODULATION","RAKE ERCEIVER FOR SPREAD SPECTRUM SIGNAL DEMODULATION","INTERFERENCE CANCELLATION IN A SIGNAL","METHOD AND APPARATUS FOR IMPLEMENTING PROJECTIONS IN SIGNAL PROCESSING APPLICATIONS","RAKE RECEIVER FOR SPREAD SPECTRUM SIGNAL DEMODULATION","METHOD AND APPARATUS TO COMPUTE THE GEOLOCATION OF A COMMUNICATION DEVICE USING ORTHOGONAL PROJECTIONS","SERIAL CANCELLATION RECEIVER DESIGN FOR A CODED SIGNAL PROCESSING ENGINE","CONSTRUCTION OF AN INTERFERENCE MATRIX FOR A CODED SIGNAL PROCESSING ENGINE","METHOD AND APPARATUS FOR SELECTIVELY APPLYING INTERFERENCE CANCELLATION IN SPREAD SPECTRUM SYSTEMS","SYSTEM AND METHOD FOR ADJUSTING PHASE","METHOD AND APPARATUS FOR INTERFERENCE SUPPRESSION WITH EFFICIENT MATRIX INVERSION IN A DS-CDMA SYSTEM","METHOD AND APPARATUS FOR CHANNEL AMPLITUDE ESTIMATION AND INTERFERENCE VECTOR CONSTRUCTION","Systems and methods for reducing interference in CDMA systems","INTERFERENCE CANCELLATION IN A SIGNAL","Systems and methods for location estimation in spread spectrum communication systems","INTERFERENCE MATRIX CONSTRUCTION","SYSTEMS AND METHODS FOR PARALLEL SIGNAL CANCELLATION","ORTHOGONALIZATION AND DIRECTIONAL FILTERING","Systems and methods for serial cancellation","SYSTEMS AND METHODS FOR ANALOG TO DIGITAL CONVERSION WITH A SIGNAL CANCELLATION SYSTEM OF A RECEIVER","Interference cancellation in a receive diversity system","Gain control for interference cancellation","Interference cancellation in adjoint operators for communication receivers","Systems and methods for searching interference canceled data","CONSTRUCTION OF PROJECTION OPERATORS FOR INTERFERENCE CANCELLATION","Interference selection and cancellation for CDMA communications","SERIAL CANCELLATION RECEIVER DESIGN FOR A CODED SIGNAL PROCESSING ENGINE","INTERFERENCE CANCELLATION WITHIN WIRELESS TRANSCEIVERS","ADVANCED SIGNAL PROCESSORS FOR INTERFERENCE CANCELLATION IN BASEBAND RECEIVERS","Interpolator using splines generated from an integrator stack seeded at input sample points","Optimal feedback weighting for soft-decision cancellers","Complementary linear feedback shift registers for generating advance timing masks","SOFT WEIGHTED INTERFERENCE CANCELLATION FOR CDMA SYSTEMS","VARIABLE INTERFERENCE CANCELLATION TECHNOLOGY FOR CDMA SYSTEMS","SYSTEMS AND METHODS FOR IMPLEMENTING CORDIC ROTATIONS FOR PROJECTORS AND RELATED OPERATORS","Conflict-free memory for fast walsh and inverse fast walsh transforms","Multiplication by one from a set of constants using simple circuitry","INTERFERENCE CANCELLATION IN VARIABLE CODELENGTH SYSTEMS FOR MULTI-ACCESS COMMUNICATION","ITERATIVE INTERFERENCE CANCELLATION USING MIXED FEEDBACK WEIGHTS AND STABILIZING STEP SIZES","ITERATIVE INTERFERENCE CANCELLATION USING MIXED FEEDBACK WEIGHTS AND STABILIZING STEP SIZES","ITERATIVE INTERFERENCE CANCELLATION USING MIXED FEEDBACK WEIGHTS AND STABILIZING STEP SIZES","ITERATIVE INTERFERENCE CANCELLATION USING MIXED FEEDBACK WEIGHTS AND STABILIZING STEP SIZES","Iterative interference cancellation for MIMO-OFDM receivers","INTER-SYMBOL INTERFERENCE CANCELLATION FOR WIRELESS MULTIPLE ACCESS","ITERATIVE INTERFERENCE CANCELLER FOR WIRELESS MULTIPLE-ACCESS SYSTEMS WITH MULTIPLE RECEIVE ANTENNAS","ITERATIVE INTERFERENCE CANCELLER FOR WIRELESS MULTIPLE-ACCESS SYSTEMS EMPLOYING CLOSED LOOP TRANSMIT DIVERSITY","Virtual reference timing for multi-time based systems","METHODS FOR MANAGING ALIGNMENT AND LATENCY IN INTERFERENCE CANCELLATION","METHODS FOR ESTIMATION AND INTERFERENCE CANCELLATION FOR SIGNAL PROCESSING","SYSTEMS AND METHODS FOR CONTROL OF ADVANCED RECEIVERS","ITERATIVE INTERFERENCE CANCELLATION FOR MIMO-OFDM RECEIVERS","INTERFERENCE CANCELLATION IN VARIABLE CODELENGTH SYSTEMS FOR MULTI-ACESS COMMUNICATION","ITERATIVE INTERFERENCE CANCELLATION USING MIXED FEEDBACK WEIGHTS AND STABILIZING STEP SIZES","ITERATIVE INTERFERENCE CANCELLATION USING MIXED FEEDBACK WEIGHTS AND STABILIZING STEP SIZES","INTER-SYMBOL INTERFERENCE CANCELLATION FOR WIRELESS MULTIPLE ACCESS"],"issueDate":["2002-08-06","2005-09-20","2004-03-23","2005-02-15","2004-09-07","2004-06-15","2007-01-02","2007-04-03","2010-08-31","2006-06-27","2008-09-30","2009-08-25","0000-00-00","2006-05-02","0000-00-00","2009-08-18","2009-01-06","2007-08-21","0000-00-00","2009-01-13","0000-00-00","0000-00-00","0000-00-00","0000-00-00","0000-00-00","0000-00-00","2008-04-15","2008-12-09","2010-08-31","0000-00-00","2014-06-24","0000-00-00","2011-01-25","2010-10-05","2010-10-19","0000-00-00","0000-00-00","2010-04-13","2011-08-02","2010-04-20","2010-05-04","2010-05-11","0000-00-00","2010-06-08","2010-11-02","2009-11-24","0000-00-00","2011-12-27","2011-08-23","2012-05-15","2012-07-10","2011-11-22","0000-00-00","2012-10-30","0000-00-00"],"patNum":["6430216","6947474","6711219","6856945","6788734","6750818","7158559","7200183","7787518","7068706","7430253","7580448","NULL","7039136","NULL","7577186","7474690","7260506","NULL","7477710","NULL","NULL","NULL","NULL","NULL","NULL","7359465","7463609","7787572","NULL","8761321","NULL","7876810","7808937","7818357","NULL","NULL","7697595","7991088","7702048","7711075","7715508","NULL","7733941","7826516","7623602","NULL","8085889","8005128","8179946","8218697","8064498","NULL","8300745","NULL"],"pctNum":["NULL","NULL","NULL","NULL","NULL","NULL","NULL","NULL","NULL","NULL","NULL","NULL","NULL","NULL","NULL","NULL","NULL","NULL","NULL","NULL","NULL","NULL","NULL","NULL","NULL","NULL","NULL","NULL","NULL","NULL","NULL","NULL","NULL","NULL","NULL","NULL","NULL","NULL","NULL","NULL","NULL","NULL","NULL","NULL","NULL","NULL","NULL","NULL","NULL","NULL","NULL","NULL","NULL","NULL","NULL"],"publDate":["0000-00-00","2002-07-11","2004-01-29","2004-02-12","2002-11-28","2004-01-29","2004-02-05","2004-03-18","2007-08-09","2004-04-29","2004-07-15","2004-05-20","2004-07-29","2004-08-05","2004-10-21","2005-02-10","2005-02-10","2005-04-07","2005-06-09","2005-07-28","2006-06-15","2005-05-12","2006-07-13","2005-08-04","2005-08-18","2006-10-12","2005-08-18","2007-02-01","2006-10-12","2007-03-15","2006-10-12","2007-07-19","2006-10-12","2006-10-12","2007-06-07","2007-09-06","2007-10-11","2007-11-15","2007-05-17","2007-05-17","2007-05-17","2007-05-17","2007-05-17","2007-05-17","2007-05-17","2007-05-17","2008-03-20","0000-00-00","0000-00-00","2009-06-04","2010-08-19","2010-09-23","2010-07-15","2010-09-02","2010-09-02"],"publNum":["NULL","2002009002","2004001786","2004003053","2002017648","2004001731","2004002230","2004005230","2007018348","2004008122","2004013644","2004009843","2004014609","2004015123","2004020823","2005003106","2005003102","2005007584","2005012308","2005016303","2006012568","2005010127","2006015328","2005016935","2005018036","2006022905","2005018049","2007002529","2006022790","2007006139","2006022790","2007016840","2006022785","2006022773","2007013024","2007020879","2007023981","2007026370","2007011013","2007011013","2007011013","2007011013","2007011013","2007011019","2007011013","2007011013","2008006918","NULL","NULL","2009014177","2010020885","2010023898","2010017785","2010022082","2010022082"],"inventors":["NULL"],"applNumSize":55,"patNumSize":55,"inventionTitleFirst":"RAKE RECEIVER FOR SPREAD SPECTRUM SIGNAL DEMODULATION","applNumFirst":"09612602","filingDateFirst":"2000-07-07","intlPublDateFirst":"0001-01-01T00:00:00Z","intlRegNumFirst":"NULL","issueDateFirst":"2002-08-06","patNumFirst":"6430216","publDateFirst":"0000-00-00","publNumFirst":""},{"id":"24706-648","displayId":"24706-648","reelNo":"24706","frameNo":"648","recordedDate":"2010-07-19","pageCount":"33","conveyanceText":"CORRECTIVE ASSIGNMENT TO CORRECT THE ASSIGNEE INFORMATION PREVIOUSLY RECORDED ON REEL 024202 FRAME 0630. ASSIGNOR(S) HEREBY CONFIRMS THE ASSIGNMENT.","corrName":"BARCELO & HARRISON LLP","corrAddress1":"2901 WEST COAST HIGHWAY, SUITE 200","corrAddress2":"NEWPORT BEACH, CA 92663","patAssignorEarliestExDate":"2010-04-05","patAssignorName":["Tensorcomm Inc"],"patAssigneeName":["Rambus Inc"],"patAssigneeAddress1":["4440 EL CAMINO REAL"],"patAssigneeAddress2":[""],"patAssigneeCity":["LOS ALTOS"],"patAssigneeState":["CALIFORNIA"],"patAssigneeCountryName":["\r"],"patAssigneePostcode":["94022"],"applNum":["09612602","09765553","09988218","09988219","10141999","10178541","10247836","10294834","10669954","10686359","10686828","10686829","10699360","10763346","10838924","10935015","10935669","10959618","11003881","11005679","11009981","11012817","11035141","11049112","11100935","11100940","11103138","11192763","11204606","11223713","11233636","11253045","11266928","11272411","11287175","11301771","11398229","11432580","11451685","11451688","11451932","11452027","11475458","11479401","11491674","11509920","11522074","11858074","11893707","12274551","12707507","12727880","12731779","12731915","12731960"],"filingDate":["2000-07-07","2001-01-18","2001-11-19","2001-11-19","2002-05-08","2002-06-25","2002-09-20","2002-11-15","2003-09-23","2003-10-15","2003-10-15","2003-10-15","2003-10-31","2004-01-23","2004-05-03","2004-09-07","2004-09-07","2004-10-06","2004-12-03","2004-12-07","2004-12-10","2004-12-14","2005-01-13","2005-04-11","2005-04-07","2005-04-07","2005-04-11","2005-07-29","2005-08-15","2005-09-09","2005-09-23","2005-10-18","2005-11-04","2005-11-10","2005-11-23","2005-12-13","2006-04-05","2006-05-11","2006-06-13","2006-06-13","2006-06-13","2006-06-13","2006-08-28","2006-06-29","2006-07-24","2006-08-25","2006-09-15","2007-09-19","2007-08-17","2008-11-20","2010-02-17","2010-03-19","2010-03-25","2010-03-25","2010-03-25"],"intlRegNum":["NULL","NULL","NULL","NULL","NULL","NULL","NULL","NULL","NULL","NULL","NULL","NULL","NULL","NULL","NULL","NULL","NULL","NULL","NULL","NULL","NULL","NULL","NULL","NULL","NULL","NULL","NULL","NULL","NULL","NULL","NULL","NULL","NULL","NULL","NULL","NULL","NULL","NULL","NULL","NULL","NULL","NULL","NULL","NULL","NULL","NULL","NULL","NULL","NULL","NULL","NULL","NULL","NULL","NULL","NULL"],"inventionTitle":["RAKE RECEIVER FOR SPREAD SPECTRUM SIGNAL DEMODULATION","RAKE ERCEIVER FOR SPREAD SPECTRUM SIGNAL DEMODULATION","INTERFERENCE CANCELLATION IN A SIGNAL","METHOD AND APPARATUS FOR IMPLEMENTING PROJECTIONS IN SIGNAL PROCESSING APPLICATIONS","RAKE RECEIVER FOR SPREAD SPECTRUM SIGNAL DEMODULATION","METHOD AND APPARATUS TO COMPUTE THE GEOLOCATION OF A COMMUNICATION DEVICE USING ORTHOGONAL PROJECTIONS","SERIAL CANCELLATION RECEIVER DESIGN FOR A CODED SIGNAL PROCESSING ENGINE","CONSTRUCTION OF AN INTERFERENCE MATRIX FOR A CODED SIGNAL PROCESSING ENGINE","METHOD AND APPARATUS FOR SELECTIVELY APPLYING INTERFERENCE CANCELLATION IN SPREAD SPECTRUM SYSTEMS","SYSTEM AND METHOD FOR ADJUSTING PHASE","METHOD AND APPARATUS FOR INTERFERENCE SUPPRESSION WITH EFFICIENT MATRIX INVERSION IN A DS-CDMA SYSTEM","METHOD AND APPARATUS FOR CHANNEL AMPLITUDE ESTIMATION AND INTERFERENCE VECTOR CONSTRUCTION","Systems and methods for reducing interference in CDMA systems","INTERFERENCE CANCELLATION IN A SIGNAL","Systems and methods for location estimation in spread spectrum communication systems","INTERFERENCE MATRIX CONSTRUCTION","SYSTEMS AND METHODS FOR PARALLEL SIGNAL CANCELLATION","ORTHOGONALIZATION AND DIRECTIONAL FILTERING","Systems and methods for serial cancellation","SYSTEMS AND METHODS FOR ANALOG TO DIGITAL CONVERSION WITH A SIGNAL CANCELLATION SYSTEM OF A RECEIVER","Interference cancellation in a receive diversity system","Gain control for interference cancellation","Interference cancellation in adjoint operators for communication receivers","Systems and methods for searching interference canceled data","CONSTRUCTION OF PROJECTION OPERATORS FOR INTERFERENCE CANCELLATION","Interference selection and cancellation for CDMA communications","SERIAL CANCELLATION RECEIVER DESIGN FOR A CODED SIGNAL PROCESSING ENGINE","INTERFERENCE CANCELLATION WITHIN WIRELESS TRANSCEIVERS","ADVANCED SIGNAL PROCESSORS FOR INTERFERENCE CANCELLATION IN BASEBAND RECEIVERS","Interpolator using splines generated from an integrator stack seeded at input sample points","Optimal feedback weighting for soft-decision cancellers","Complementary linear feedback shift registers for generating advance timing masks","SOFT WEIGHTED INTERFERENCE CANCELLATION FOR CDMA SYSTEMS","VARIABLE INTERFERENCE CANCELLATION TECHNOLOGY FOR CDMA SYSTEMS","SYSTEMS AND METHODS FOR IMPLEMENTING CORDIC ROTATIONS FOR PROJECTORS AND RELATED OPERATORS","Conflict-free memory for fast walsh and inverse fast walsh transforms","Multiplication by one from a set of constants using simple circuitry","INTERFERENCE CANCELLATION IN VARIABLE CODELENGTH SYSTEMS FOR MULTI-ACCESS COMMUNICATION","ITERATIVE INTERFERENCE CANCELLATION USING MIXED FEEDBACK WEIGHTS AND STABILIZING STEP SIZES","ITERATIVE INTERFERENCE CANCELLATION USING MIXED FEEDBACK WEIGHTS AND STABILIZING STEP SIZES","ITERATIVE INTERFERENCE CANCELLATION USING MIXED FEEDBACK WEIGHTS AND STABILIZING STEP SIZES","ITERATIVE INTERFERENCE CANCELLATION USING MIXED FEEDBACK WEIGHTS AND STABILIZING STEP SIZES","Iterative interference cancellation for MIMO-OFDM receivers","INTER-SYMBOL INTERFERENCE CANCELLATION FOR WIRELESS MULTIPLE ACCESS","ITERATIVE INTERFERENCE CANCELLER FOR WIRELESS MULTIPLE-ACCESS SYSTEMS WITH MULTIPLE RECEIVE ANTENNAS","ITERATIVE INTERFERENCE CANCELLER FOR WIRELESS MULTIPLE-ACCESS SYSTEMS EMPLOYING CLOSED LOOP TRANSMIT DIVERSITY","Virtual reference timing for multi-time based systems","METHODS FOR MANAGING ALIGNMENT AND LATENCY IN INTERFERENCE CANCELLATION","METHODS FOR ESTIMATION AND INTERFERENCE CANCELLATION FOR SIGNAL PROCESSING","SYSTEMS AND METHODS FOR CONTROL OF ADVANCED RECEIVERS","ITERATIVE INTERFERENCE CANCELLATION FOR MIMO-OFDM RECEIVERS","INTERFERENCE CANCELLATION IN VARIABLE CODELENGTH SYSTEMS FOR MULTI-ACESS COMMUNICATION","ITERATIVE INTERFERENCE CANCELLATION USING MIXED FEEDBACK WEIGHTS AND STABILIZING STEP SIZES","ITERATIVE INTERFERENCE CANCELLATION USING MIXED FEEDBACK WEIGHTS AND STABILIZING STEP SIZES","INTER-SYMBOL INTERFERENCE CANCELLATION FOR WIRELESS MULTIPLE ACCESS"],"issueDate":["2002-08-06","2005-09-20","2004-03-23","2005-02-15","2004-09-07","2004-06-15","2007-01-02","2007-04-03","2010-08-31","2006-06-27","2008-09-30","2009-08-25","0000-00-00","2006-05-02","0000-00-00","2009-08-18","2009-01-06","2007-08-21","0000-00-00","2009-01-13","0000-00-00","0000-00-00","0000-00-00","0000-00-00","0000-00-00","0000-00-00","2008-04-15","2008-12-09","2010-08-31","0000-00-00","2014-06-24","0000-00-00","2011-01-25","2010-10-05","2010-10-19","0000-00-00","0000-00-00","2010-04-13","2011-08-02","2010-04-20","2010-05-04","2010-05-11","0000-00-00","2010-06-08","2010-11-02","2009-11-24","0000-00-00","2011-12-27","2011-08-23","2012-05-15","2012-07-10","2011-11-22","0000-00-00","2012-10-30","0000-00-00"],"patNum":["6430216","6947474","6711219","6856945","6788734","6750818","7158559","7200183","7787518","7068706","7430253","7580448","NULL","7039136","NULL","7577186","7474690","7260506","NULL","7477710","NULL","NULL","NULL","NULL","NULL","NULL","7359465","7463609","7787572","NULL","8761321","NULL","7876810","7808937","7818357","NULL","NULL","7697595","7991088","7702048","7711075","7715508","NULL","7733941","7826516","7623602","NULL","8085889","8005128","8179946","8218697","8064498","NULL","8300745","NULL"],"pctNum":["NULL","NULL","NULL","NULL","NULL","NULL","NULL","NULL","NULL","NULL","NULL","NULL","NULL","NULL","NULL","NULL","NULL","NULL","NULL","NULL","NULL","NULL","NULL","NULL","NULL","NULL","NULL","NULL","NULL","NULL","NULL","NULL","NULL","NULL","NULL","NULL","NULL","NULL","NULL","NULL","NULL","NULL","NULL","NULL","NULL","NULL","NULL","NULL","NULL","NULL","NULL","NULL","NULL","NULL","NULL"],"publDate":["0000-00-00","2002-07-11","2004-01-29","2004-02-12","2002-11-28","2004-01-29","2004-02-05","2004-03-18","2007-08-09","2004-04-29","2004-07-15","2004-05-20","2004-07-29","2004-08-05","2004-10-21","2005-02-10","2005-02-10","2005-04-07","2005-06-09","2005-07-28","2006-06-15","2005-05-12","2006-07-13","2005-08-04","2005-08-18","2006-10-12","2005-08-18","2007-02-01","2006-10-12","2007-03-15","2006-10-12","2007-07-19","2006-10-12","2006-10-12","2007-06-07","2007-09-06","2007-10-11","2007-11-15","2007-05-17","2007-05-17","2007-05-17","2007-05-17","2007-05-17","2007-05-17","2007-05-17","2007-05-17","2008-03-20","0000-00-00","0000-00-00","2009-06-04","2010-08-19","2010-09-23","2010-07-15","2010-09-02","2010-09-02"],"publNum":["NULL","2002009002","2004001786","2004003053","2002017648","2004001731","2004002230","2004005230","2007018348","2004008122","2004013644","2004009843","2004014609","2004015123","2004020823","2005003106","2005003102","2005007584","2005012308","2005016303","2006012568","2005010127","2006015328","2005016935","2005018036","2006022905","2005018049","2007002529","2006022790","2007006139","2006022790","2007016840","2006022785","2006022773","2007013024","2007020879","2007023981","2007026370","2007011013","2007011013","2007011013","2007011013","2007011013","2007011019","2007011013","2007011013","2008006918","NULL","NULL","2009014177","2010020885","2010023898","2010017785","2010022082","2010022082"],"inventors":["NULL"],"applNumSize":55,"patNumSize":55,"inventionTitleFirst":"RAKE RECEIVER FOR SPREAD SPECTRUM SIGNAL DEMODULATION","applNumFirst":"09612602","filingDateFirst":"2000-07-07","intlPublDateFirst":"0001-01-01T00:00:00Z","intlRegNumFirst":"NULL","issueDateFirst":"2002-08-06","patNumFirst":"6430216","publDateFirst":"0000-00-00","publNumFirst":""}],"assignments":[],"names":[],"general":{"original_number":"11009981","patent_number":"11009981 Interference cancellation in a receive diversity system","logo_1":"https://patentrack.com/resources/shared/images/company-default.png","logo_2":"https://patentrack.com/resources/shared/images/user-default.png","copyright":"2020 copyright PatenTrack."},"box_menu":{"border_color":["#e8665d","#e8a41c","#c1ed0e","#ed0e2f"],"background_color":["#fae3e3","#f5f5d7","#d7f0f5","#f5d7dc"]},"title":"Interference cancellation in a receive diversity system","comment":"","asset_type":5,"all_boxes":[{"id":1,"segment":0,"border_color":"#363636","border_px":"1","background_color":"#222222","dimension":"100x30","type":"Inventor","shape":"rectangle"},{"id":2,"segment":1,"border_color":"#363636","border_px":"1","background_color":"#222222","dimension":"100x30","type":"Ownership","shape":"rectangle"},{"id":3,"segment":2,"border_color":"#363636","border_px":"1","background_color":"#222222","dimension":"100x30","type":"Security","shape":"rectangle"},{"id":4,"segment":3,"border_color":"#363636","border_px":"1","background_color":"#222222","dimension":"100x30","type":"Licenses","shape":"rectangle"},{"id":5,"segment":3,"border_color":"#363636","border_px":"1","background_color":"#222222","dimension":"100x30","type":"3rdParties","shape":"rectangle"}],"legend":[{"id":2,"tooltip":"Ownership","color":"#E60000","type":0,"explanation":""},{"id":3,"tooltip":"Name Change","color":"#2493f2","type":0,"explanation":""},{"id":4,"tooltip":"Security","color":"#ffaa00","type":0,"explanation":""},{"id":5,"tooltip":"License","color":"#E6E600","type":0,"explanation":""},{"id":7,"tooltip":"Release","color":"#70A800","type":0,"explanation":""},{"id":8,"tooltip":"License End","color":"#E38B4F","type":0,"explanation":""}],"line":[{"id":1,"assignment_no1":1,"color":"#E60000","type":"Ownership","type_line":"Solid","ref_id":0,"start_id":2,"end_id":3,"box_creator_id":3,"box_creator_id2":0,"popup":["17069-370"],"comment":[{"17069-370":["",""]}],"user_files":[""],"tooltip":"Ownership","date":"Apr 04,2005","date_1":1112572800,"document1":"https://patentrack.com/resources/shared/data/assignment-pat-17069-370.pdf","document2":"","note1":"","pdf1":"","note2":"","pdf2":"","popuptop":"17069-370","popupbottom":""},{"id":2,"assignment_no1":1,"color":"#E60000","type":"Ownership","type_line":"Solid","ref_id":0,"start_id":1,"end_id":3,"box_creator_id":0,"box_creator_id2":0,"popup":["17069-370"],"comment":[{"17069-370":["",""]}],"user_files":[""],"tooltip":"Ownership","date":"Apr 05,2005","date_1":1112659200,"document1":"https://patentrack.com/resources/shared/data/assignment-pat-17069-370.pdf","document2":"","note1":"","pdf1":"","note2":"","pdf2":"","popuptop":"17069-370","popupbottom":""},{"id":3,"assignment_no1":2,"color":"#E60000","type":"Ownership","type_line":"Solid","ref_id":0,"start_id":4,"end_id":3,"box_creator_id":0,"box_creator_id2":4,"popup":["24202-617"],"comment":[{"24202-617":["",""]}],"user_files":[""],"tooltip":"Ownership","date":"Apr 05,2010","date_1":1270425600,"document1":"https://patentrack.com/resources/shared/data/assignment-pat-24202-617.pdf","document2":"","note1":"","pdf1":"","note2":"","pdf2":"","popuptop":"24202-617","popupbottom":""},{"id":4,"assignment_no1":3,"color":"#E60000","type":"Ownership","type_line":"Solid","ref_id":0,"start_id":3,"end_id":5,"box_creator_id":5,"box_creator_id2":0,"popup":["24202-630"],"comment":[{"24202-630":["",""]}],"user_files":[""],"tooltip":"Ownership","date":"Apr 05,2010","date_1":1270425600,"document1":"https://patentrack.com/resources/shared/data/assignment-pat-24202-630.pdf","document2":"","note1":"","pdf1":"","note2":"","pdf2":"","popuptop":"24202-630","popupbottom":""},{"id":5,"assignment_no1":4,"color":"#E60000","type":"Ownership","type_line":"Solid","ref_id":0,"start_id":3,"end_id":5,"box_creator_id":0,"box_creator_id2":0,"popup":["24706-648"],"comment":[{"24706-648":["",""]}],"user_files":[""],"tooltip":"Ownership","date":"Apr 05,2010","date_1":1270425600,"document1":"https://patentrack.com/resources/shared/data/assignment-pat-24706-648.pdf","document2":"","note1":"","pdf1":"","note2":"","pdf2":"","popuptop":"24706-648","popupbottom":""}]}